LICENSE
MANIFEST.in
README.txt
jscssmin.py
requirements.txt
setup.py
jscssmin.egg-info/PKG-INFO
jscssmin.egg-info/SOURCES.txt
jscssmin.egg-info/dependency_links.txt
jscssmin.egg-info/requires.txt
jscssmin.egg-info/top_level.txt
scripts/jscssmin